rooster/__init__.py
rooster/__main__.py
rooster/_cache.py
rooster/_changelog.py
rooster/_cli.py
rooster/_config.py
rooster/_git.py
rooster/_github.py
rooster/_pyproject.py
rooster/_testing.py
rooster/_versions.py
rooster_blue-0.0.9.dist-info/METADATA
rooster_blue-0.0.9.dist-info/WHEEL
rooster_blue-0.0.9.dist-info/entry_points.txt
rooster_blue-0.0.9.dist-info/RECORD
