Metadata-Version: 2.1
Name: rooster-blue
Version: 0.0.9
Summary: 
Home-page: https://github.com/zanieb/rooster
Author: Zanie
Author-email: contact@zanie.dev
Requires-Python: >=3.11,<4.0
Classifier: Development Status :: 3 - Alpha
Classifier: Environment :: Plugins
Classifier: Intended Audience :: Developers
Classifier: License :: OSI Approved :: MIT License
Classifier: Natural Language :: English
Classifier: Operating System :: OS Independent
Classifier: Programming Language :: Python
Classifier: Programming Language :: Python :: 3
Classifier: Programming Language :: Python :: 3.11
Classifier: Programming Language :: Python :: 3.10
Classifier: Programming Language :: Python :: 3.7
Classifier: Programming Language :: Python :: 3.8
Classifier: Programming Language :: Python :: 3.9
Classifier: Topic :: Software Development
Classifier: Topic :: Software Development :: Libraries
Classifier: Typing :: Typed
Requires-Dist: hishel (>=0.0.24,<0.0.25)
Requires-Dist: httpx (>=0.25.0,<0.26.0)
Requires-Dist: marko (>=2.0.2,<3.0.0)
Requires-Dist: packaging (>=23.1,<24.0)
Requires-Dist: pydantic (>=2.4.2,<3.0.0)
Requires-Dist: pygit2 (>=1.13.1,<2.0.0)
Requires-Dist: tqdm (>=4.66.1,<5.0.0)
Requires-Dist: typer (>=0.9.0,<0.10.0)
Project-URL: Repository, https://github.com/zanieb/rooster
